Metadata-Version: 2.1
Name: ahmedmahos
Version: 0.1
Summary: spam call , email and telegram sms
Author: AHMED-Alhrrani
Classifier: Programming Language :: Python :: 3
Classifier: Operating System :: OS Independent
Classifier: License :: OSI Approved :: MIT License
License-File: LICENSE.txt